common_wrangler/__init__.py
common_wrangler/_version.py
common_wrangler/add2dict.py
common_wrangler/common.py
common_wrangler/fill_tpl.py
common_wrangler/rename_files.py
common_wrangler/update_slurm.py
common_wrangler-0.3.8.1.dist-info/LICENSE
common_wrangler-0.3.8.1.dist-info/METADATA
common_wrangler-0.3.8.1.dist-info/WHEEL
common_wrangler-0.3.8.1.dist-info/entry_points.txt
common_wrangler-0.3.8.1.dist-info/top_level.txt
common_wrangler-0.3.8.1.dist-info/RECORD
