Metadata-Version: 2.1
Name: common-wrangler
Version: 0.3.8.1
Summary: UNKNOWN
Home-page: UNKNOWN
Author: Heather B Mayes
Author-email: hmayes@hmayes.com
License: MIT
Platform: Linux
Platform: Mac OS-X
Platform: Unix
Platform: Windows
Requires-Python: >=3.5
Requires-Dist: numpy
Requires-Dist: six
Requires-Dist: matplotlib
